flask_wtforms_tutorial_al_test/__init__.py
flask_wtforms_tutorial_al_test/forms.py
flask_wtforms_tutorial_al_test/routes.py
flask_wtforms_tutorial_al_test/static/css/forms.css
flask_wtforms_tutorial_al_test/static/css/home.css
flask_wtforms_tutorial_al_test/static/css/style.css
flask_wtforms_tutorial_al_test/static/css/success.css
flask_wtforms_tutorial_al_test/templates/analytics.jinja2
flask_wtforms_tutorial_al_test/templates/contact.jinja2
flask_wtforms_tutorial_al_test/templates/index.jinja2
flask_wtforms_tutorial_al_test/templates/layout.jinja2
flask_wtforms_tutorial_al_test/templates/signup.jinja2
flask_wtforms_tutorial_al_test/templates/success.jinja2
flask_wtforms_tutorial_al_test-0.1.1.dist-info/entry_points.txt
flask_wtforms_tutorial_al_test-0.1.1.dist-info/LICENSE
flask_wtforms_tutorial_al_test-0.1.1.dist-info/WHEEL
flask_wtforms_tutorial_al_test-0.1.1.dist-info/METADATA
flask_wtforms_tutorial_al_test-0.1.1.dist-info/RECORD
