Metadata-Version: 2.1
Name: flask-wtforms-tutorial-al-test
Version: 0.1.1
Summary: Tutorial to implement forms in your Flask app.
Home-page: https://hackersandslackers.com/flask-wtforms-forms/
License: MIT
Keywords: Flask,Forms,Flask-WTF,MVC,Tutorial
Author: Alok Singh
Author-email: alok2k5singh@outlook.com
Maintainer: Alok Singh
Maintainer-email: alok2k5singh@outlook.com
Requires-Python: >=3.8,<4.0
Classifier: License :: OSI Approved :: MIT License
Classifier: Programming Language :: Python :: 3
Classifier: Programming Language :: Python :: 3.8
Classifier: Programming Language :: Python :: 3.9
Requires-Dist: email_validator
Requires-Dist: flask
Requires-Dist: flask-wtf
Requires-Dist: python-dotenv
Project-URL: Documentation, https://hackersandslackers.com/flask-wtforms-forms/
Project-URL: Repository, https://github.com/hackersandslackers/flask-wtform-tutorial/
Project-URL: issues, https://github.com/hackersandslackers/flask-wtform-tutorial/issues
